LICENSE
MANIFEST.in
README.md
VERSION
setup.py
openagents/Disk.py
openagents/DiskReader.py
openagents/DiskWriter.py
openagents/JobContext.py
openagents/JobRunner.py
openagents/Logger.py
openagents/NodeConfig.py
openagents/OpenAgentsNode.py
openagents/RunnerConfig.py
openagents/__init__.py
openagents_node_sdk.egg-info/PKG-INFO
openagents_node_sdk.egg-info/SOURCES.txt
openagents_node_sdk.egg-info/dependency_links.txt
openagents_node_sdk.egg-info/requires.txt
openagents_node_sdk.egg-info/top_level.txt