Metadata-Version: 2.1
Name: openagents-node-sdk
Version: 0.3.3
Summary: A Python SDK for OpenAgents Nodes
Author: OpenAgents
License-File: LICENSE
